examples/__init__.py
examples/basic_usage.py
examples/chat_example.py
examples/embedding_example.py
examples/generate_example.py
examples/quickstart.py
examples/version_example.py
tools/__init__.py
tools/install_ollama.py
utils/__init__.py
utils/common.py
utils/model_constants.py
wheelhouse/__init__.py
ollama_toolkit-0.1.9.dist-info/METADATA
ollama_toolkit-0.1.9.dist-info/WHEEL
ollama_toolkit-0.1.9.dist-info/entry_points.txt
ollama_toolkit-0.1.9.dist-info/top_level.txt
ollama_toolkit-0.1.9.dist-info/RECORD
