Metadata-Version: 2.2
Name: ollama_toolkit
Version: 0.1.9
Summary: A comprehensive Python client library for the Ollama API
Home-page: https://github.com/Ace1928/ollama_toolkit
Author: Lloyd Handyside, Eidos
Author-email: Lloyd Handyside <ace1928@gmail.com>, Eidos <eidos@gmail.com>
License: MIT
Project-URL: repository, https://github.com/Ace1928/ollama_toolkit
Keywords: ollama,ai,llm,language models,toolkit,eidos
Classifier: Development Status :: 4 - Beta
Classifier: Intended Audience :: Developers
Classifier: License :: OSI Approved :: MIT License
Classifier: Programming Language :: Python :: 3
Classifier: Programming Language :: Python :: 3.8
Classifier: Programming Language :: Python :: 3.9
Classifier: Programming Language :: Python :: 3.10
Classifier: Programming Language :: Python :: 3.11
Classifier: Programming Language :: Python :: 3.12
Requires-Python: >=3.6
Provides-Extra: dev
Requires-Dist: black; extra == "dev"
Requires-Dist: flake8; extra == "dev"
Requires-Dist: mypy; extra == "dev"
Requires-Dist: pytest-cov; extra == "dev"
Requires-Dist: sphinx; extra == "dev"
Requires-Dist: twine; extra == "dev"
